README.md
setup.py
csvUtils/__init__.py
csvUtils/csv.py
dhlUtils.egg-info/PKG-INFO
dhlUtils.egg-info/SOURCES.txt
dhlUtils.egg-info/dependency_links.txt
dhlUtils.egg-info/not-zip-safe
dhlUtils.egg-info/top_level.txt