Metadata-Version: 1.0
Name: dhlUtils
Version: 0.1.1
Summary: All the tools a dhl developer needs in python
Home-page: UNKNOWN
Author: dhl-uu
Author-email: dh.developers@uu.nl
License: MIT
Platform: UNKNOWN
